sopel_rtfm/__init__.py
sopel_rtfm/plugin.py
sopel_rtfm-0.5.0.dist-info/COPYING
sopel_rtfm-0.5.0.dist-info/METADATA
sopel_rtfm-0.5.0.dist-info/WHEEL
sopel_rtfm-0.5.0.dist-info/entry_points.txt
sopel_rtfm-0.5.0.dist-info/top_level.txt
sopel_rtfm-0.5.0.dist-info/RECORD
